litic/LiticAPI.py
litic/Utils.py
litic/__init__.py
litic/exceptions/Exceptions.py
litic/exceptions/__init__.py
litic-0.1.10.dist-info/LICENSE.txt
litic-0.1.10.dist-info/METADATA
litic-0.1.10.dist-info/WHEEL
litic-0.1.10.dist-info/top_level.txt
litic-0.1.10.dist-info/RECORD
