Metadata-Version: 2.1
Name: litic
Version: 0.1.10
Summary: A LITIC Service is a set of procedures that can be called from an external program using HTTP.
Home-page: https://litic.com
Author: LITIC Team
Author-email: development@litic.com
License: MIT
Keywords: LITIC
Platform: UNKNOWN
Classifier: Development Status :: 3 - Alpha
Classifier: Intended Audience :: Developers
Classifier: License :: OSI Approved :: MIT License
Classifier: Programming Language :: Python :: 2.7
Classifier: Programming Language :: Python :: 3.5
Requires-Dist: requests
Requires-Dist: pandas
Requires-Dist: six
